donifarakan/__init__.py
donifarakan/client.py
donifarakan/config.py
donifarakan/server.py
donifarakan/utils.py
donifarakan/models/__init__.py
donifarakan/routes/__init__.py
donifarakan-0.1.3.dist-info/LICENSE
donifarakan-0.1.3.dist-info/METADATA
donifarakan-0.1.3.dist-info/WHEEL
donifarakan-0.1.3.dist-info/top_level.txt
donifarakan-0.1.3.dist-info/RECORD
