Metadata-Version: 2.1
Name: donifarakan
Version: 0.1.3
Summary: Donifarakan is a federated learning framework designed specially for the finance sector (banks, fintech companies, etc.), where the stakeholders will train a generalized model on their local data without sharing them in order to make predictions, prevent market risks, assess news impacts on the stock market, and more.  
Home-page: https://github.com/adamstrvor/donifarakan
Author: Adama Seydou Traore
Author-email: adamaseydoutraore86@gmail.com
Classifier: Programming Language :: Python :: 3
Classifier: License :: OSI Approved :: MIT License
Classifier: Operating System :: OS Independent
License-File: LICENSE
Requires-Dist: fastapi
Requires-Dist: Flask
Requires-Dist: uvicorn
Requires-Dist: pydantic
Requires-Dist: scikit-learn
Requires-Dist: pandas
Requires-Dist: numpy
Requires-Dist: matplotlib
Requires-Dist: tensorflow
Requires-Dist: termcolor
Requires-Dist: openpyxl
Requires-Dist: nltk
Requires-Dist: requests
Requires-Dist: kagglehub
Requires-Dist: shap
Requires-Dist: lime
Requires-Dist: seaborn
